metepy/__init__.py
metepy/aef_.pyd
metepy/basef_.pyd
metepy/drawf_.pyd
metepy/gisf_.pyd
metepy/npf_.pyd
metepy/rstscaf_.pyd
metepy/trackf_.pyd
metepy-0.1.3.dist-info/METADATA
metepy-0.1.3.dist-info/WHEEL
metepy-0.1.3.dist-info/top_level.txt
metepy-0.1.3.dist-info/RECORD
