Metadata-Version: 2.1
Name: metepy
Version: 0.1.3
Requires-Python: >=3.9, <3.10
Requires-Dist: numpy (>=1.18.0)
Requires-Dist: pandas (>=1.0.0)
Requires-Dist: meteva (>=1.0.0)
